FORM/__init__.py
FORM/cli (ABT1945W8L's conflicted copy 2016-12-12).py
FORM/cli.py
FORM/design_by_testing.py
FORM/form (ABT1945W8L's conflicted copy 2016-12-12).py
FORM/form.py
FORM/monte_carlo.py
FORM/parser.py
FORM_cal-0.2.1.dist-info/DESCRIPTION.rst
FORM_cal-0.2.1.dist-info/METADATA
FORM_cal-0.2.1.dist-info/RECORD
FORM_cal-0.2.1.dist-info/WHEEL
FORM_cal-0.2.1.dist-info/metadata.json
FORM_cal-0.2.1.dist-info/top_level.txt
