Metadata-Version: 2.0
Name: FORM-cal
Version: 0.2.1
Summary: Taylor series approximation of the performance function of different stochastic variables.
Home-page: http://ritchievink.com
Author: Ritchie Vink
Author-email: ritchie46@gmail.com
License: MIT License
Platform: UNKNOWN
Requires-Dist: matplotlib
Requires-Dist: numpy
Requires-Dist: scipy
Requires-Dist: sympy
